{ "1": {
    "words": {
      "apt":"~하는 경향이 있는 / 적당한",
      "astonish":"놀라게 하다",
      "chronically":"만성적으로",
      "daub":"흠뻑 칠하다",
      "domain":"지역, 영토 / 분야, 영역",
      "enthusiastic":"열성적인",
      "extend":"(어떤 거리까지) 걸쳐 있다 / 확장하다, 늘리다",
      "feat":"업적",
      "fulfill":"성취하다 / 만족시키다",
      "give over to":"헌신하다, 바치다",
      "heavy":"무거운; 고된",
      "hibernation":"동면",
      "illusion":"착각, 오해",
      "intrigue":"(주의, 관심을) 끌다 / 음모를 꾸미다",
      "luxuriant":"무성한, 풍부한",
      "magnitude":"정도; 크기",
      "maintain":"주장하다 / 지속하다",
      "monitor":"조사하다",
      "outbreak":"(전염병 등의) 만연, 창궐 / 폭발",
      "periodically":"주기적으로",
      "release":"해방시키다 / 뿜다, 방출하다 / (묶인 것을) 풀다",
      "rendering":"연주, 공연",
      "renowned":"유명한",
      "reproduce":"복제하다 / 번식하다",
      "rugged":"울퉁불퉁한",
      "self-sufficient":"자급자족하는, 제힘으로 살아가는",
      "speculative":"이론적인 / 사색적인",
      "stimulate":"자극하다, 격려하다",
      "subordinate":"종속적인",
      "torrential":"격렬한"
    }
  },
  "2": {
    "words": {
      "address":"주소 / 강연",
      "assume":"맡다 / ~인 척하다 / ~라고 생각하다, 추측하다",
      "attain":"도달하다 / 성취하다, 이루다",
      "boast":"자랑하다",
      "capacity":"용적 / 능력",
      "cede":"양도하다, 포기하다",
      "decline":"거절하다 / 하락하다, 쇠퇴하다",
      "desert":"버리다",
      "disassemble":"분해하다",
      "dispose":"배치하다, 배열하다",
      "dispose of":"처리하다",
      "erode":"침식하다, 부식되다",
      "fairly":"꽤 / 공정하게",
      "glossy":"빛나는, 광택이 나는",
      "grounds":"근거, 이유",
      "hallmark":"특징",
      "ideal":"이상적인, 전형의 / 관념적인",
      "inhabit":"거주하다",
      "laborious":"근면한",
      "linger":"남다 / 꾸물거리다, 질질 끌다",
      "loathe":"혐오하다",
      "mimic":"모방하다",
      "model":"견본",
      "observe":"관찰하다' 알아채다 / 준수하다",
      "plentiful":"풍부한",
      "preoccupied":"몰두한",
      "property":"자산 / 특성",
      "recurring":"되풀이되는",
      "rooted":"뿌리 깊은, 정착한",
      "thoroughly":"철저히, 완전히"
    }
  },
  "3": {
    "words": {
      "afford":"주다",
      "announce":"공포하다",
      "a wide range of":"다양한",
      "chance":"가능성; 기회",
      "chart":"(지도 등을) 작성하다",
      "engage":"약속하다 / 예약하다 / 고용하다",
      "esteem":"존경하다; 중하게 여기다",
      "evidence":"증거; 징후",
      "fertile":"비옥한",
      "generate":"발생시키다",
      "innate":"타고난",
      "invaluable":"매우 귀중한",
      "irreparable":"돌이킬 수 없는",
      "maxim":"격언; 행동 원칙",
      "object":"항의하다 / 목적",
      "outstanding":"뛰어난 / 미결제의",
      "patron":"후원자 / 고객",
      "predominate":"우세하다, 지배력을 갖다",
      "previous":"이전의",
      "premise":"전제",
      "primitive":"원시적인 / 기본적인",
      "proficiency":"능숙한",
      "proposition":"제안",
      "questionable":"의심스러운",
      "rife with":"가득찬, 수없이 많은",
      "shield":"보호하다",
      "solitary":"외딴, 고독한",
      "stick":"달라붙다, 고수하다",
      "stimulus":"자극, 격력",
      "stir":"자극하다",
      "taboo":"금기",
      "thrive":"번성하다",
      "vagary":"예측 불허의 변화",
      "wane":"감소하다, 쇠퇴하다",
      "view":"견해, 의견 / 간주하다"
    }
  },
  "4": {
    "words": {
      "achieve":"성취하다",
      "anchor":"고정시키다",
      "attribute":"~의 탓으로 돌리다 / 특성",
      "brisk":"활기 있는",
      "codify":"(체계적으로) 정리하다",
      "consummate":"뛰어난; 완전한",
      "descent":"하강 / 혈통, 기원",
      "disseminate":"퍼뜨리다",
      "earn":"획득하다",
      "emergence":"출현, 부상",
      "facilitate":"(일을) 용이하게 하다",
      "fervent":"열정적인",
      "fine":"미세한, 섬세한; 가느다란",
      "frivolous":"사소한",
      "giant":"거인",
      "golden age":"황금 시대, 전성기",
      "grasp":"붙잡다 / 이해하다, 파악하다",
      "hamstrung":"무력한; 불구의",
      "haphazard":"되는대로의, 우연의",
      "incidental":"중요하지 않은; 우연한",
      "initiate":"시작하다",
      "make up":"창작하다, 창안하다",
      "manifold":"가지각색의",
      "obliterate":"제거하다",
      "period":"시대",
      "proceed":"나아가다",
      "procure":"얻다",
      "professional":"전문적인",
      "redundancy":"여분' 장황",
      "responsible":"책임이 있는",
      "sharp":"날카로운, 예리한 / 급격한",
      "supplement":"보충하다 / 추가, 부가",
      "suspend":"연기하다 / 중지하다 / 매달다",
      "tailored":"맞추어진"
    }
  },
  "5": {
    "words": {
      "aimlessly":"목적 없이",
      "ally":"~와 동맹하다, 연합하다",
      "anonymous":"익명의",
      "anticipate":"예견하다",
      "archaic":"원시적인; 구식의",
      "asset":"이점, 장점",
      "behavior":"행동",
      "ceaseless":"끊임없는",
      "change":"변화시키다",
      "confederacy":"연합, 동맹",
      "cut":"절단하다",
      "disturbance":"동요, 혼란",
      "elucidate":"명료하게 하다",
      "encroachment":"침범",
      "entice":"유혹하다",
      "equivocally":"애매하게",
      "exterminate":"근절하다",
      "fortify":"강화하다",
      "formerly":"이전에",
      "immunity":"면제",
      "improve":"개선하다",
      "in retrospect":"되돌아보면, 회상하면",
      "lose sight of":"잊다",
      "nuts and bolts":"기본",
      "permit":"허락하다",
      "radical":"근본적인 / 급진적인",
      "rarely":"드물게, 좀처럼 ~ 않는",
      "sparse":"빈약한, 부족한",
      "sting":"얼얼하다, 쓰리다",
      "support":"지지하다 / 부양하다",
      "tangible":"견디다",
      "train":"~로 향하게 하다",
      "unambiguous":"명확한",
      "virtually":"사실상 / 거의",
      "wary":"조심(경계)하는",
      "wealth":"풍부함",
      "wiggle":"이리저리 흔들다"
    }
  },
  "6": {
    "words": {
      "agile":"민첩한",
      "ample":"넓은 / 충분한",
      "arbitrarily":"임의로",
      "attest":"입증하다",
      "break with":"관ㄱ례를 끊다",
      "brightness":"빛",
      "conjure":"불러내다, 상기시키다 / 간청하다",
      "contrive":"고안해내다",
      "correspondence":"일치 / (편지로 하는) 통신",
      "durable":"지속적인",
      "dwarf":"난쟁이",
      "enigmatic":"알기 어려운",
      "extinct":"멸종된",
      "fabricate":"만들어내다",
      "flake":"파편",
      "harm":"손해",
      "innocent":"결백한",
      "in the course of":"~동안에",
      "in vain":"헛되이",
      "inconsequential":"하찮은, 사소한",
      "leave":"떠나다",
      "liken":"비유하다",
      "literally":"실제로",
      "moderate":"온건한",
      "prolong":"연장하다",
      "purify":"정화하다, 깨끗이 하다",
      "reasonable":"이치에 맞는",
      "refined":"정제된",
      "retain":"유지(보유)하다",
      "scarce":"드분; 부족한",
      "scope":"범위",
      "shabby":"초라한",
      "short-lived":"단기간의",
      "solidify":"결속시키다",
      "substantial":"튼튼한 / 상당한",
      "vacant":"텅 빈",
      "wizened":"시든, 주름진",
      "zone":"지역"
    }
  },
  "7": {
    "words": {
      "abolish":"폐지하다",
      "adage":"속담, 금언",
      "aesthetic":"미적인",
      "affect":"~에 영향을 미치다 / ~인 체하다",
      "alteration":"변경",
      "amenity":"편의 시설",
      "approximately":"대략",
      "artisan":"숙련공",
      "bear":"운반하다 / 산출하다, 생기게 하다 / (무게를) 지탱하다, 견디다",
      "bountiful":"풍부한",
      "constituent":"구성하는, 구성 요소의",
      "dispute":"논쟁하다 / 논쟁",
      "faculty":"능력",
      "field":"분야",
      "guiltless":"결백한",
      "influx":"유입",
      "inundate":"물에 잠기게 하다",
      "lexicon":"어휘",
      "lure":"유혹하다",
      "mixture":"혼합(물)",
      "mount":"오르다 / 증가하다",
      "mundane":"평범한",
      "nearly":"거의",
      "outstrip":"능가하다, 뛰어나다",
      "pertinent":"관련된, 적절한",
      "preclude":"그만두게 하다, 막다",
      "refrain":"삼가다, 중단하다",
      "roughly":"대략",
      "semblance":"외관 / 유사함",
      "sophisticated":"복잡한",
      "stage":"단계",
      "thick":"빽빽한",
      "thus":"따라서",
      "tiny":"작은",
      "verge":"경계, 찰나"
    }
  },
  "8": {
    "words": {
      "abort":"중단하다",
      "acquire":"얻다",
      "affection":"애정",
      "agree":"동의하다",
      "alert":"경계하는 / 경고하다",
      "allure":"(마음을) 끌다, 유혹하다",
      "amplify":"늘리다",
      "arid":"메마른",
      "ascribe":"~의 탓으로 돌리다",
      "barge":"배",
      "compensate":"보상하다; 상쇄하다",
      "configure":"~의 형체로 만들다",
      "drastic":"과격한, 극단적인",
      "embarrass":"무안케 하다",
      "focus":"집중하다",
      "function":"기능, 역할 / 기능하다",
      "gathering":"수집; 모임",
      "haul":"끌어당기다",
      "immediate":"인접한",
      "increase":"확대하다",
      "loom":"어렴풋이 나타나다",
      "overtax":"지나치게 과세하다",
      "paradox":"모순",
      "pervasive":"퍼지는",
      "pleasing":"마음에 드는, 기분 좋은",
      "primary":"근본적인",
      "proper":"적당한",
      "recur":"재발하다",
      "save for":"~을 제외하고",
      "serve":"소용이 되다, 도움이 되다",
      "simulate":"흉내 내다; 가장하다",
      "speck":"얼룩, 소량",
      "strive":"노력하다",
      "suppose":"가정하다",
      "surprise":"놀라게 하다",
      "treat":"다루다, 대하다",
      "undertake":"(책임, 역할을) 맡다; 착수하다",
      "variant":"변형"
    }
  },
  "9": {
    "words": {
      "abandon":"그만두다, 버리다",
      "antidote":"치료법",
      "at hand":"사용 가능한",
      "bear in mind":"명심하다",
      "boost":"증대시키다",
      "conspicuous":"뚜렷한",
      "critical":"중요한 / 위험한",
      "discriminate":"식별하다",
      "dorsal":"등(부분)의",
      "eliminate":"제거하다",
      "fuse":"녹다, 녹이다",
      "hinterland":"배후지, 오지",
      "in earnest":"진지한",
      "laden":"(짐을) 실은",
      "lumber":"판재, 재목",
      "mirror":"반영하다",
      "mutual":"상호 간의; 공동의",
      "obtainable":"손에 넣을 수 있는",
      "patch":"수선하다 / 작은 부분, 지역",
      "protest":"항의하다",
      "recall":"회상하다",
      "reflection":"반영",
      "regain":"~을 되찾다",
      "reinforce":"강화하다",
      "relevant":"관련된, 적절한",
      "reminisce":"추억하다",
      "route":"길",
      "secrete":"분비하다",
      "semiarid":"반건조한",
      "soothe":"진정시키다, 완화하다",
      "stay":"머무르다",
      "surplus":"나머지, 잔여",
      "toothed":"들쑥날쑥한",
      "transform":"변형시키다",
      "uniformly":"균일하게",
      "utilitarian":"실용적인",
      "variety":"다양성 / 종류",
      "wonderful":"놀라운"
    }
  },
  "10": {
    "words": {
      "advantage":"이익",
      "arise from":"~에서 기인하다",
      "barrier":"장애물, 장벽",
      "betray":"배신하다",
      "bind":"묶다",
      "blur":"흐리게 하다",
      "circumvent":"우회하다",
      "clumsy":"서투른",
      "commence":"시작하다",
      "conduct":"행동 / (빛, 열 등을) 전도하다",
      "conserve":"보존하다",
      "contradiction":"모순",
      "culminate":"~로 끝나다",
      "delineate":"윤곽을 그리다",
      "donation":"기부(금), 기증(물)",
      "embark on":"시작하다",
      "foundation":"기초",
      "fundamental":"근본적인",
      "handful":"소량, 소수",
      "height":"정상, 절정",
      "identical":"동일한",
      "impediment":"장애",
      "justify":"(정당성을) 증명하다",
      "lament":"슬퍼하다, 애도하다",
      "microorganism":"미생물",
      "origin":"발생, 근원",
      "peculiarity":"특성",
      "physical":"물질의 / 육체의",
      "predict":"예측하다",
      "progress":"발전",
      "scoop":"긁어모으다",
      "score":"얻다 / 악보, 악곡",
      "scrap":"파편",
      "singularly":"각별히",
      "skilled":"숙련된",
      "stem from":"~에서 유래하다",
      "subsidize":"후원하다",
      "unanimity":"(만장)일치"
    }
  },
  "11":{
    "words":{
      "account":"(있었던 일에 대한) 설명",
      "alloy":"혼합하다",
      "barely":"거의 ~않다",
      "carry on":"~을 계속하다",
      "cohesion":"결속",
      "coincide":"동시에 일어나다 / 의견이 일치하다",
      "colossal":"거대한",
      "considerable":"중요한 / 상당한",
      "converge":"한데 모이다",
      "conviction":"신념",
      "covet":"갈망하다",
      "defect":"결점",
      "defection":"변절, 탈당",
      "dull":"지루한",
      "endeavor":"노력하다, 애쓰다",
      "flock":"무리, 떼",
      "grant":"주다",
      "hustle":"서두르다 / 밀다",
      "intermediate":"중간의",
      "intolerant":"옹졸한, 편협한",
      "kind":"친절한, 인정 많은 / 유형, 종류",
      "limit":"경계, 한계 / 제한하다",
      "margin":"가장자리",
      "militia":"시민군",
      "moreover":"게다가",
      "necessary":"필수적인",
      "obstruct":"막다, 방해하다",
      "on the spot":"즉시",
      "partial":"편파적인, 부분적인",
      "placid":"평온한",
      "porosity":"구멍' 다공성",
      "reform":"개정하다, 개선하다",
      "rigid":"단단한, 뻣뻣한 / 엄격한",
      "scarcity":"부족, 결핍"
    }
  },
  "12":{
    "words":{
      "adaptable":"융통성 있는, 적응성 있는",
      "adhesion":"달라붙음, 부착",
      "blame":"비난하다",
      "chaotic":"무질서한",
      "comprehend":"이해하다",
      "decided":"분명한; 단호한",
      "displace":"대체하다",
      "enclose":"애워싸다",
      "entail":"~을 수반하다",
      "excel":"능가하다, 빼어나다",
      "expend":"(시간, 노력 등을) 쓰다, 들이다",
      "facility":"재능, 소질",
      "genre":"유형",
      "illustrate":"묘사하다",
      "infrastructure":"기반, 하부 구조",
      "inhibit":"억제하다; 금지하다",
      "involve":"~을 수반하다",
      "lease":"임차하다",
      "likewise":"또한; 마찬가지로",
      "limited":"제한된",
      "lodge in":"박다, 꽂아 넣다",
      "mingle":"섞이다, 혼합되다",
      "obligation":"의무",
      "oblige":"강요하다",
      "offer":"제공하다, 제안하다",
      "on occasion":"가끔",
      "pare":"껍질을 벗기다; 삭감하다",
      "predominately":"주로",
      "preordained":"예정된",
      "render":"~가 되게 하다 / 주다 / ~을 표현하다",
      "renown":"명성",
      "repel":"물리치다",
      "sanitation":"공중위생",
      "scorching":"몹시 뜨거운(더운)",
      "secluded":"외딴",
      "spare":"절약하다 / 주다, (시간을) 할애하다",
      "stimulating":"활기(자극)을 주는",
      "typify":"대표하다, 특징을 나타내다",
      "wholesale":"대규모의"
    }
  },
  "13": {
    "words": {
      "admire":"존경하다",
      "adroit":"능숙한",
      "ambivalent":"불확실한, 상반된 감정이 공존하는",
      "camouflage":"감추다, 위장하다",
      "composed":"차분한 / 작성된",
      "conceal":"숨기다",
      "deliberate":"신중한 / 의도적인",
      "exhilarate":"들뜨게 하다",
      "exposure":"폭로, 발각",
      "glow":"빛나다",
      "hiatus":"중단, 단절",
      "incinerate":"태우다",
      "ineffectively":"비효과적으로",
      "inert":"움직일 수 없는",
      "luster":"광채",
      "massive":"거대한, 막대한",
      "occupy":"(주의, 마음을) 끌다, 사로잡다",
      "precede":"앞서다, 우선하다",
      "prove":"입증하다",
      "purchase":"얻다, 획득하다",
      "restrict":"제한하다",
      "rupture":"불화; 파열 / 찢다, 파열시키다",
      "scrutiny":"정밀 조사",
      "seductive":"유혹적인",
      "seep":"스며들다",
      "segment":"부분",
      "shatter":"박살 내다",
      "shock":"충격을 주다, 놀라게 하다",
      "significant":"중요한",
      "slab":"조각",
      "slaughter":"학살하다",
      "strife":"싸움",
      "style":"방식",
      "sustained":"지속적인",
      "temperance":"자제, 절제",
      "tremendous":"엄청난",
      "vivid":"선명한; 생생한",
      "wedge":"억지로 밀어 낳다"
    }
  },
  "14": {
    "words": {
      "actually":"실제로",
      "adorn":"장식하다",
      "calculate":"추정하다, 어림잡다",
      "claim":"요구하다",
      "commemorate":"기념하다",
      "conformity":"일치",
      "copious":"풍부한",
      "desire":"열망하다; 요구하다",
      "diligently":"열심히",
      "enthrall":"매혹하다",
      "feast":"축제 / 배불리 먹다",
      "gather":"모으다",
      "gauge":"평가하다, 판단하다",
      "glue":"접착시키다",
      "grand":"웅장한",
      "hearten":"격려하다",
      "hub":"중심",
      "hybrid":"잡종, 혼합물",
      "impetus":"자극",
      "improvise":"(연주, 연설 등을) 즉흥적으로 하다",
      "irresistible":"매혹적인; 저항할 수 없는",
      "incised":"새겨진",
      "inherent in":"내재된",
      "juvenile":"어린",
      "main":"주요한",
      "negligence":"부주의, 태만",
      "outweigh":"~보다 뛰어나다",
      "pigment":"색소",
      "plausible":"그럴듯한",
      "prudent":"조심성 있는, 신중한",
      "revise":"수정하다",
      "spirit":"정신",
      "skillful":"숙련된",
      "tenet":"원칙",
      "transformation":"변화",
      "traverse":"가로지르다",
      "unbearably":"극도로",
      "variable":"변하기 쉬운",
      "while":"~동안에; ~하는 한 / ~할 지라도; ~와는 반대로"
    }
  },
  "15": {
    "words": {
      "affluent":"부유한, 풍족한",
      "aggravate":"악화시키다",
      "cling to":"달라붙다, 고수하다",
      "craft":"솜씨 있게 만들다",
      "crest":"정상",
      "critic":"비평가",
      "cross-hatching":"음영",
      "decimate":"많은 사람을 죽이다",
      "disciple":"제자",
      "disclose":"(사실 등을) 밝히다",
      "disposition":"성질, 기질",
      "dissimilar":"다른",
      "dominant":"우세한",
      "effect":"영향; 결과",
      "enhance":"향상시키다, 개선하다",
      "enunciate":"분명하게 발음하다",
      "eradicate":"근절하다",
      "harsh":"가혹한",
      "heritage":"전통, 유산",
      "inappropriate":"부적당한",
      "insolent":"무례한",
      "jeopardy":"위험",
      "luxury":"사치",
      "manipulate":"조종하다, 다루다",
      "mock":"조롱하다",
      "precious":"귀중한",
      "regard":"관심; 호감, 존경",
      "return":"되돌아가다",
      "set":"~을 놓다",
      "spacious":"넓은",
      "spectator":"구경꾼",
      "strict":"엄겪한",
      "swift":"빠른",
      "synchronize":"동시에 일어나다",
      "throughout":"~의 도처에",
      "undermine":"약화시키다",
      "upset":"뒤엎다, 전복시키다 / 당황하게 하다",
      "virtuous":"덕 있는",
      "wrangle":"논쟁하다; 말다툼하다",
      "withdraw":"물러나다",
      "worship":"숭배하다"
    }
  },
  "16": {
    "words": {
      "alternative":"대안 / 대용이 되는",
      "analogous":"유사한",
      "annually":"매년",
      "awkward":"서투른",
      "capability":"재능",
      "cleanse":"깨끗이 하다",
      "collide":"충돌하다",
      "congested":"혼잡한",
      "contemporary":"현대의; 동시대의",
      "cover":"포함하다",
      "deceitful":"허위의",
      "exception":"제외",
      "feature":"특징",
      "fractious":"성미가 까다로운",
      "incorporate":"통합하다",
      "intimate":"친숙한",
      "invariably":"예외 없이, 반드시",
      "inveigle":"꾀다, 유혹하다",
      "lead":"단서 / 야기하다",
      "loop":"묶다",
      "lucid":"명료한, 명쾌한",
      "master":"정통하다",
      "option":"선택",
      "paradoxical":"역설적인",
      "plumage":"깃털",
      "prevent":"~을 방해하다, 막다",
      "profuse":"풍부한",
      "revolve":"회전하다",
      "scale":"(기어) 오르다 /  정도, 단계",
      "scant":"줄이다",
      "sensational":"세상을 들끓게 하는",
      "shallow":"얕은",
      "sort":"분류하다 / 종류",
      "stylus":"첨필",
      "typically":"일반적으로",
      "vary":"다르다",
      "voracious":"만족할 줄 모르는, 탐욕적인"
    }
  },
  "17": {
    "words": {
      "absolute":"완전한",
      "adapted":"개조된",
      "chamber":"(작은) 방",
      "compact":"압축하다 / 조밀한, 밀집한",
      "complacency":"만족",
      "compulsory":"강제적인",
      "concomitant":"동시에 일어나는",
      "condense":"압축(응축)하다",
      "conform":"순응하다, 따르다",
      "consistent":"모순이 없는, 일관된",
      "constrain":"억제하다",
      "contagious":"전염성 있는",
      "counterpart":"(동등한 자격의) 대응물",
      "debris":"잔해",
      "decisive":"결정적인",
      "disdain":"경멸하다",
      "element":"구성 요소",
      "erratic":"불규칙적인, 변덕스러운",
      "exhaust":"다 써버리다 / 지치게 하다",
      "expand":"확장하다",
      "flattering":"아부하는",
      "full-blown":"성숙한",
      "henceforth":"앞으로, 차후",
      "inadvertently":"뜻하지 않게, 우연히",
      "intricate":"복잡한",
      "mammoth":"거대한",
      "merely":"단지",
      "ordinary":"보통의, 평범한",
      "plain":"분명한 / 꾸밈없는, 간소한",
      "popular":"대중적인",
      "reconcile":"화해시키다, 조정하다",
      "reexamine":"재검토하다",
      "requirement":"조건, 조항",
      "revolutionize":"~에 혁명을 일으키다",
      "rival":"경쟁자 / 경쟁하다",
      "shovel":"(삽으로) 파다",
      "succinct":"간결한",
      "tie":"관계"
    }
  },
  "18": {
    "words": {
      "ability":"능력",
      "accessible":"이용 가능한, 접근하기 쉬운",
      "accord":"주다, 수여하다; 일치하다",
      "appear":"~인 듯하다, ~인 것 같이 보인다",
      "be rooted in":"~에 근거를 두다, ~에서 유래하다",
      "bog":"습지",
      "collaborate":"협력하다",
      "crucible":"도가니, 용광로",
      "curb":"제한(억제)하다",
      "cycle":"주기",
      "deem":"~라고 여기다",
      "devout":"독실한",
      "disperse":"흩어지게 하다",
      "economical":"절약하는",
      "eventually":"결국",
      "faint":"희미한",
      "financial":"재정상의",
      "frighten":"두렵게 하다",
      "geognosy":"지질학",
      "give way to":"물러가다, 양보하다",
      "immense":"거대한, 막대한",
      "impact":"영향",
      "ingenuity":"독창성, 창의력",
      "in keeping with":"~와 일치하여",
      "job":"일, 직무",
      "lethargic":"무기력한",
      "meager":"부족한",
      "parody":"풍자적 변형",
      "refuge":"피난처, 은신처",
      "rural":"시골의",
      "scrub":"북북 문지르다",
      "secure":"확보하다 / 안전한",
      "skepticism":"회의(론)",
      "so far":"지금까지",
      "spark":"야기하다",
      "speculation":"추측",
      "terrain":"지역",
      "tumult":"혼란, 소란",
      "unlimited":"무한한",
      "vagarious":"변덕스러운",
      "volume":"책"
    }
  },
  "19": {
    "words": {
      "advent":"출현",
      "article":"(개개의) 물품",
      "assembly":"의회",
      "associated":"연관된",
      "aware":"~을 알고 있는",
      "bank":"물가, 기슭",
      "by and large":"전반적으로, 대체로",
      "challenge":"난제 / 도전하다",
      "compress":"압축하다",
      "consort":"교제하다",
      "construe":"해석하다",
      "correct":"고치다, 바로잡다",
      "curious":"호기심이 강한",
      "deadly":"치명적인",
      "defeated":"패배한",
      "deplete":"고갈시키다",
      "edge":"가장자리",
      "elude":"피하다",
      "endow":"부여하다",
      "exceedingly":"지나칠 정도로",
      "far-reaching":"방대한",
      "fluster":"혼란시키다",
      "guess":"추측하다",
      "importance":"중요한",
      "interfere":"방해하다, 간섭하다",
      "irksome":"지루한",
      "last":"마지막의 / 지속하다",
      "manage":"관리하다",
      "mastery":"전문 기술, 숙달",
      "monopolize":"독점하다",
      "overcome":"이기다, 정복하다",
      "ratify":"승인하다",
      "replica":"복제",
      "shift":"옮기다; 바꾸다",
      "stride":"진보, 발전",
      "subject to":"(영향을) 받기 쉬운",
      "successive":"연속적인",
      "transition":"변화",
      "undertaking":"사업, 과제"
    }
  },
  "20": {
    "words": {
      "accurate":"정확한",
      "advisor":"고문",
      "antagonize":"대항하다",
      "architecture":"구조",
      "assure":"확신시키다",
      "bond":"유대, 결속",
      "brave":"대담한",
      "crucial":"중대한",
      "complement":"보충, 보완",
      "comprise":"구성되다",
      "counter to":"~와 정반대로",
      "daring":"용감한",
      "devise":"고안하다",
      "duplicate":"복사(복제)하다",
      "dwindle":"줄다, 감소시키다",
      "embody":"구현하다 / ~을 포함하다",
      "etch":"식각하다, 새기다",
      "flash":"번쩍이다",
      "imaginable":"상상할 수 있는",
      "infectious":"전염성의",
      "innumerable":"무수한",
      "invariable":"불변의",
      "meditate":"숙고하다",
      "opposite":"(성질, 의미 등이) 정반대의 / 정반대",
      "outdo":"~을 능가하다",
      "outline":"개요; 윤곽",
      "parallel":"~와 유사한 / ~에 필적하다",
      "preeminent":"탁월한",
      "reassuring":"용기를 북돋는",
      "regulate":"조절하다",
      "respectful":"공손한",
      "shrink":"줄어들다",
      "skill":"기술",
      "steadily":"지속적으로",
      "struggle":"싸우다",
      "subsequence":"이어서 일어나는 것",
      "warrant":"정당화하다",
      "ware":"제품",
      "yet":"그럼에도 불구하고"
    }
  },
  "21": {
    "words": {
      "abundance":"풍부함",
      "adaptability":"적용성, 융통성",
      "arrest":"체포하다",
      "assigned":"정해진",
      "be at odds with":"~와 불화하다",
      "curiously":"신기하게도",
      "dense":"짙은",
      "deploy":"(전략적으로) 배치하다",
      "discreet":"분별력 있는",
      "entire":"전체의",
      "evident":"분명한",
      "extensive":"넓은",
      "extinguish":"(불을) 끄다 / 소멸시키다",
      "feeble":"연약한",
      "flavor":"특징 / 맛, 풍미",
      "fragmentary":"단편적인",
      "in charge of":"~에 책임이 있는",
      "minor":"중요치 않은",
      "parcel out":"분할(분배)하다",
      "perceive":"알아차리다",
      "piece":"조각 / 잇다, 접합하다",
      "pledge":"맹세",
      "portray":"묘사하다",
      "project":"계획 / 돌출하다",
      "region":"지역",
      "safe":"안전한",
      "search":"탐색하다, 조사하다",
      "seethe":"(화가 나서) 속이 끓다",
      "shortcoming":"결점",
      "special":"특별한",
      "survey":"조사하다",
      "temperament":"성질",
      "tool":"도구",
      "uninitiated":"미숙한",
      "vanish":"사라지다",
      "vile":"사악한",
      "worldly":"세속적인",
      "wreck":"파괴하다"
    }
  },
  "22": {
    "words": {
      "accustomed":"익숙한",
      "allege":"주장하다, 우기다",
      "at the expense of":"~의 비용(대가)로",
      "breed":"기르다",
      "chisel":"조각하다",
      "conclusive":"결정적인",
      "costly":"비싼",
      "crack down":"~을 엄히 단속하다",
      "degree":"정도",
      "delicate":"섬세한",
      "devote":"헌신하다",
      "die":"죽다",
      "distribute":"분배하다",
      "emergency":"위기, 위급",
      "fatal":"치명적인",
      "guilty":"유죄의",
      "hazard":"위험",
      "in any case":"여하튼",
      "incite":"자극하다",
      "moist":"축축한",
      "ornament":"장식하다",
      "peripheral":"주변의",
      "precipitous":"성급한",
      "primarily":"주로 / 본래, 처음에",
      "primeval":"원시의",
      "raw":"가공하지 않은",
      "reject":"거절하다",
      "replenish":"보충하다",
      "rot":"부패하다",
      "ruin":"파괴하다",
      "runoff":"벌마, 넘쳐흐름",
      "shorten":"줄이다",
      "spoil":"망치다. 손상시키다",
      "standard":"기준 / 보통의",
      "stipulation":"조건",
      "strikingly":"두드러지게",
      "subtract":"빼다",
      "thaw":"녹다, 녹이다",
      "unpin":"핀(핀 종류의 것)을 빼다"
    }
  },
  "23": {
    "words": {
      "akin to":"~와 유사한, ~에 가까운",
      "appealing":"매력적인",
      "approach":"접근법, 방법 / 접근하다",
      "argue":"논쟁하다",
      "assert":"주장하다",
      "brace":"받치다, 보강하다",
      "catastrophic":"비참한, 비극적인",
      "clarify":"명료하게 하다",
      "constantly":"지속적으로",
      "deception":"속임수, 사기",
      "distinct":"별개의 / 뚜렷한",
      "edition":"(간행물)판",
      "elaborate":"복잡한, 정교한",
      "flaw":"결점",
      "flood":"범람시키다",
      "floods of":"다수의, 쇄도하는",
      "habitat":"거주지",
      "hint":"암시",
      "intensify":"강화하다",
      "intentional":"고의적인",
      "kin":"친척",
      "make one's way":"나아가다",
      "measure":"측정하다",
      "minute":"미세한; 정밀한",
      "notwithstanding":"~에도 불구하고",
      "profound":"심오한",
      "protect":"보호하다",
      "receive":"받다, 얻다",
      "relevance":"적절, 타당성",
      "reliance":"의존",
      "represent":"묘사하다, 표현하다 / 대표하다",
      "require":"요구하다",
      "resemble":"닮다",
      "resolve":"결정하다 / 해결하다",
      "retard":"지체시키다",
      "roster":"명부",
      "scenic":"풍경이 아름다운"
    }
  },
  "24": {
    "words": {
      "absurd":"불합리한 / 어리석은",
      "activity":"활기",
      "assort":"분류하다",
      "beam":"빛나다",
      "break":"부수다 / (짧은) 휴식",
      "bromide":"진부한 말(생각)",
      "common":"공통의",
      "consciously":"의도적으로",
      "context":"배경",
      "damage":"손상, 손해",
      "detach":"분리하다",
      "dormant":"활동하지 않는",
      "environment":"환경",
      "essential":"필수적인",
      "heighten":"늘리다",
      "hinder":"방해하다",
      "impose":"강요하다",
      "ingenious":"독창적인",
      "insignificant":"사소한",
      "keen":"예리한",
      "lodge":"거처(피난처)를 제공하다 / 숙박하다",
      "power":"영향력, 힘",
      "prominent":"탁월한",
      "provided":"만약 ~이라면",
      "put together":"결합시키다",
      "reflect":"숙고하다 / 반영하다, 나타내다",
      "relinquish":"포기하다, 버리다",
      "representative":"전형적인",
      "scan":"조사하다",
      "sever":"절단하다, 분리하다",
      "shortly":"곧",
      "showcase":"전시하다",
      "succession":"연속",
      "summit":"정상, 꼭대기",
      "token":"상징, 표시",
      "transmit":"전달하다",
      "useful":"유익한, 도움이 되는",
      "vestige":"흔적"
    }
  },
  "25": {
    "words": {
      "aim":"목표하다 / 목적",
      "allocate":"책정하다; 분배하다",
      "attributed to":"~에서 기인한, ~로 설명되는",
      "authenticate":"입증하다, 증명하다",
      "confuse":"혼란시키다",
      "debate":"논쟁",
      "detractor":"험담하는 사람",
      "disguise":"속이다, 감추다",
      "dissent":"의견을 달리하다",
      "distinguish":"구별하다",
      "draw":"끌다",
      "drawback":"결점",
      "dye":"염료, 물감",
      "emit":"발산하다",
      "expose":"드러내다",
      "flawless":"흠 없는",
      "frustrate":"좌절시키다",
      "full":"완전한 / 상세한",
      "indicate":"넌지시 비추다",
      "initially":"처음에",
      "innovative":"기발한, 혁신적인",
      "landslide":"산사태",
      "malady":"병",
      "minimize":"줄이다 / 과소평가하다",
      "order":"명령 / 질서, 조화",
      "prohibit":"금지하다",
      "reduce":"감소시키다",
      "reveal":"드러내다",
      "shed light on":"~을 명백히 하다",
      "sink":"가라앉다",
      "size":"크기",
      "slope":"경사",
      "subside":"진정되다",
      "take place":"발생하다",
      "though":"그러나 / ~이지만, 비록 ~일지라도",
      "underground":"비밀의"
    }
  },
  "26": {
    "words": {
      "antipathy":"반감",
      "applicable":"적용 가능한, 적절한",
      "blot out":"가리다",
      "bold":"대담한",
      "boom":"번성하다",
      "characteristic":"독특한 / 특성",
      "clear":"명쾌한",
      "coarse":"거친, 천한",
      "concentrate":"집중하다 / 모으다",
      "contemplate":"심사숙고하다",
      "cripple":"손상시키다",
      "demanding":"힘든, 큰 노력을 요하는",
      "deviate":"벗어나다",
      "discover":"확인하다, 찾아내다",
      "discrete":"구별되는",
      "encompass":"포함하다",
      "entertain":"즐겁게 하다",
      "far-sighted":"현명한",
      "fluctuate":"변동하다",
      "halt":"멈추다",
      "incessantly":"끊임없이",
      "leading":"우세한, 주된",
      "modify":"변경하다",
      "mutation":"변이, 변화",
      "obelisk":"방첨탑, 오벨리스크",
      "pastime":"기분 전환",
      "rather than":"~대신에",
      "receptacle":"그릇, 용기",
      "rely":"의지하다",
      "remote":"외딴, 멀리 떨어진",
      "rotten":"썩은, 부패한",
      "rove":"배회하다",
      "shoddy":"조악한, (질이) 떨어지는",
      "shred":"(갈기갈기) 찢다",
      "simply":"단지",
      "span":"기간 / ~에 걸치다, 이르다",
      "stun":"놀라게 하다",
      "tranquil":"평온한, 차분한"
    }
  },
  "27": {
    "words": {
      "assistance":"원조",
      "avoid":"~을 피하다",
      "best-suited":"가장 적절한",
      "bridle":"굴레",
      "classify":"분류하다",
      "collectively":"공동으로",
      "comparable":"유사한",
      "cultivator":"경작자",
      "designated":"지정된",
      "detrimental":"해로운, 불리한",
      "differentiate":"구별하다",
      "display":"보여 주다",
      "emissary":"사절, 특사",
      "enact":"제정하다",
      "evenly":"고르게, 일관되게",
      "expedience":"편의",
      "genuinely":"정말로",
      "immediately":"즉시, 당장",
      "important":"중요한",
      "inconceivable":"상상도 못할",
      "in progress":"진행 중인",
      "it followed that S V":"그 결과로서 ~가 되었다",
      "keep in touch":"연락을 유지하다",
      "massacre":"대량학살",
      "mean":"~을 의미하다 / 비열한",
      "mute":"무언의",
      "participate":"함께 하다",
      "pit":"(사람, 기술 등을) ~와 대항시키다 / 구멍",
      "raise":"올리다",
      "rare":"드문",
      "respectively":"각각",
      "seemingly":"보기에",
      "sporadically":"때때로, 간헐적으로",
      "stringent":"엄한",
      "superficial":"외면의",
      "timid":"소심한",
      "transport":"운송하다",
      "unavoidable":"불가피한",
      "uniform":"일관성 있는",
      "unsubstantial":"비현실적인"
    }
  },
  "28": {
    "words": {
      "aptly":"적절히",
      "attract":"(마음을) 끌다",
      "beverage":"음료수",
      "blunt":"무딘",
      "bustling":"부산한",
      "control":"지배하다",
      "controversy":"논쟁",
      "dichotomy":"양분, 이분",
      "disruption":"중단",
      "enthusiasm":"열정",
      "episode":"하나의 사건",
      "equivalent":"동등한",
      "evoke":"일깨우다, 자아내다",
      "exotic":"기묘한, 못 보던",
      "flair":"재주, 재능",
      "flight":"탈출",
      "formidable":"무서운",
      "frugal":"절약하는",
      "fuel":"지지하다, 자극하다",
      "game":"사냥감",
      "hand in hand":"협력하여, 동반하여",
      "intermittent":"간헐적인",
      "intersect":"교차하다, 가로지르다",
      "make sense":"이치에 맞다",
      "movement":"(정치, 사회적) 운동",
      "pass through":"꿰뚫다",
      "precise":"정확한",
      "publish":"발표하다",
      "readily":"쉽게; 기꺼이",
      "record":"기록",
      "relieve":"경감하다",
      "settle down":"진정시키다",
      "shun":"피하다",
      "spectacular":"멋진, 장엄한",
      "steady":"안정된",
      "store":"따로 떼어두다, 비축하다",
      "stupid":"어리석은",
      "success":"성공, 달성",
      "tend":"돌보다",
      "wattle":"가는 막대기",
      "wrath":"분노"
    }
  },
  "29": {
    "words": {
      "acid":"신랄한",
      "amass":"모으다",
      "breakthrough":"약진, 큰 발전",
      "cause":"야기시키다, 초래하다",
      "certain":"일정한",
      "component":"성분",
      "conditional":"조건부의, ~여하에 달린",
      "confront":"직면하다",
      "consequence":"결과",
      "crack":"쪼개다, 깨뜨리다",
      "crude":"천연 그대로의, 가공하지 않은",
      "drought":"가뭄",
      "effort":"노력",
      "emerge":"나타나다",
      "endurance":"인내; 내구력",
      "euphoria":"행복감",
      "exacerbate":"더욱 심하게 하다",
      "explain":"설명하다",
      "finish":"끝내다",
      "hollow":"텅 빈",
      "lash":"묶다, 매다",
      "leisurely":"느긋한",
      "manageable":"관리할 수 있는, 감당할 수 있는",
      "note":"명성",
      "periphery":"주변부",
      "practical":"실용적인",
      "prerequisite":"필요조건",
      "relatively":"비교적으로",
      "rudimentary":"기본적인, 기초적인",
      "selected":"선택된",
      "shed":"탈피하다 / (빛 등을) 비추다",
      "spotty":"고르지 않은",
      "spread":"퍼지다, ~에 이르다",
      "staunch":"확고한, 충실한",
      "stress":"강조 / 강조하다",
      "stunted":"(성장이) 멎은",
      "trespass":"침해하다",
      "trumpet":"공표하다",
      "via":"~을 경유하다"
    }
  },
  "30": {
    "words": {
      "accumulate":"모으다",
      "antithesis":"정반대",
      "astute":"기민한",
      "be up to":"~에 달려 있다",
      "being":"생물",
      "bring about":"초래하다",
      "cache":"은닉처",
      "celebratory":"축하의, 축하하는",
      "close":"면밀한 / 차단하다",
      "cognitive":"정신적인, 인식의",
      "create":"만들어내다",
      "destroy":"파괴하다, 망치다",
      "diminutive":"작은",
      "endangered":"명종위기에 처한, 위험에 처한",
      "formative":"형성되는, 발달의",
      "founder":"실패하다",
      "glean":"모으다",
      "govern":"지배하다 / 통제하다",
      "indigenous":"토착의",
      "integrate":"통합하다",
      "interval":"(시간, 거리의) 간격",
      "largely":"대캐",
      "magnificent":"굉장히 멋진",
      "overshadow":"가리다, 어둡게하다",
      "particular":"특별한",
      "ramification":"결과",
      "rather":"약간, 다소",
      "realm":"범위, 영역",
      "rivalry":"경쟁",
      "silent":"말이 없는",
      "situate":"위치시키다",
      "sphere":"분야",
      "stealthily":"은밀히, 몰래",
      "superb":"뛰어난, 훌륭한",
      "swell":"(크기, 수량 등이) 증가하다",
      "tender":"부드러운 / 변상금",
      "velocity":"속도, 신속함",
      "wild":"야생의, 난폭한"
    }
  },
  "31": {
    "words": {
      "accompany":"동반하다",
      "adverse":"적대적인",
      "appeal":"탄원, 청원 / 매력",
      "arouse":"자극하다, 유발시키다",
      "boundary":"경계(선)",
      "bury":"가리다",
      "collective":"집합된, 축척된",
      "confine":"제한하다",
      "cumbersome":"성가신, 다루기 힘든",
      "dispensable":"없어도 되는",
      "distribution":"분배",
      "eat":"먹다",
      "entirely":"완전히",
      "equal":"동등한",
      "evaluate":"평가하다",
      "false":"잘못된",
      "focal point":"중심(지)",
      "gallant":"용감한",
      "hence":"그러므로",
      "integral":"필수적인",
      "lay down":"(규칙, 원칙 등을) 정하다",
      "launch":"착수하다",
      "magnify":"확대하다, 증대하다",
      "match":"필적하다",
      "more or less":"어느 정도, 다소",
      "nature":"특징, 성향",
      "operative":"효과적인",
      "pragmatic":"실용적인",
      "proliferate":"증식하다",
      "proven":"증명된",
      "provoke":"자극하다, 화나게 하다",
      "register":"등록하다, 기록하다 / 목록",
      "respectable":"존경할만한",
      "rig":"장비를 갖추다",
      "sterile":"불모의",
      "sufficient":"충분한",
      "transparent":"명백한",
      "uneasy":"불안한",
      "unpretentious":"수수한"
    }
  },
  "32": {
    "words": {
      "appreciably":"뚜렷하게, 상당히",
      "assess":"평가하다",
      "banish":"추방하다",
      "choice":"선택권, 대안",
      "comparatively":"비교적, 꽤",
      "consume":"소비(소모)하다",
      "excavate":"발굴하다",
      "exclude":"배제하다",
      "exert":"(힘, 능력 등을) 발휘하다",
      "extraordinary":"비범한",
      "forage":"찾아다니다",
      "fragile":"깨지기 쉬운; 연약한",
      "have nothing to do with":"~와 관계가 없다",
      "interpret":"설명하다, 해석하다",
      "lavish":"낭비하다 / 사치스런",
      "lucrative":"이익이 되는",
      "mainly":"주로",
      "manifest":"명백한 / 증명하다",
      "material":"물질적인",
      "meticulously":"주의 깊게",
      "nervous":"신경질적인",
      "obstinate":"완고한",
      "overstate":"과장하다",
      "pack together":"모이다",
      "perform":"수행하다",
      "perishable":"상하기 쉬운",
      "pound":"마구 치다",
      "prolific":"결실이 많은, 다작의",
      "proof":"증거",
      "serene":"고요한",
      "spawn":"야기하다",
      "substitute":"대체하다 / 대안",
      "surpass":"능가하다",
      "survival":"생존",
      "ubiquitous":"어디에나 존재하는",
      "undergo":"(어려운 일을) 겪다",
      "weed out":"제거하다",
      "worn-out":"지친"
    }
  },
  "33": {
    "words": {
      "adhere":"~에 달라붙다, 고수하다",
      "assertion":"주장, 단언",
      "barren":"불모의",
      "budding":"신진의",
      "central":"주요한",
      "comprehensible":"알기 쉬운",
      "concern":"관심",
      "configuration":"배치, 배열",
      "deserved":"당연히 받아야 할",
      "detect":"발견하다, 인지하다",
      "diffuse":"퍼뜨리다 (spread)",
      "exaggerate":"과장하다",
      "fetter":"구속하다, 제한하다",
      "float":"뜨다",
      "frequent":"빈번한",
      "groundless":"근거 없는",
      "hindrance":"방해, 장애(물)",
      "maneuver":"계획, 책략 / 움직이다",
      "mar":"망쳐 놓다",
      "mighty":"강력한",
      "opaque":"불투명한 / 불명료한",
      "originate":"일어나다, 생기다",
      "pace":"걸음(걸이) / 속력 / 걷다",
      "perceptibly":"알아차릴 정도로",
      "promising":"유망한",
      "punctuality":"시간 엄수",
      "rotate":"회전하다",
      "scatter":"퍼뜨리다 (widely spread)",
      "sedentary":"움직이지 않는",
      "site":"장소, 위치",
      "soak":"적시다",
      "subsist":"존속하다",
      "supremacy":"우월, 우위",
      "trigger":"일으키다",
      "tumultuous":"무질서한, 떠들썩한",
      "veritable":"실제의",
      "waste":"낭비하다",
      "weaken":"약화시키다"
    }
  },
  "34": {
    "words": {
      "accretion":"축적(물)",
      "agriculture":"농업",
      "attach":"붙이다",
      "counter":"대항하다, 반박하다",
      "crop up":"나타나다",
      "dimly":"희미하게",
      "distract":"산만하게 하다",
      "drain":"배수하다",
      "emergent":"떠오르는, 신흥의",
      "enlarge":"확대시키다",
      "excessive":"지나친",
      "exploit":"위업 / 이용하다",
      "extract":"이끌어 내다",
      "fierce":"사나운",
      "fiery":"불같은",
      "first and foremost":"무엇보다도 먼저",
      "fluctuation":"변동",
      "gradually":"점차적으로",
      "languid":"기운 없는",
      "location":"장소, 위치",
      "lengthen":"연장하다",
      "mandatory":"필수의",
      "narrate":"이야기하다",
      "noxious":"유해한",
      "once":"일단 ~하면",
      "pierce":"관통하다",
      "positive":"확신하는 / 긍정적인",
      "pretend":"~인 체하다",
      "range":"범위 / 변화하다",
      "rudiment":"기초, 기본",
      "signify":"표명하다, 나타내다",
      "simultaneously":"동시에",
      "symmetrical":"균형이 잡힌, 대칭적인",
      "testify":"증명하다, 입증하다",
      "vast":"거대한",
      "visionary":"환상의",
      "vogue":"유행",
      "weariness":"피로"
    }
  },
  "35": {
    "words": {
      "accelerate":"촉진시키다",
      "adjust":"맞추다, 조절하다",
      "a great deal of":"다량의",
      "alleviate":"완화하다",
      "aromatic":"향기로운",
      "celebrated":"유명한",
      "characterize":"특징 지우다",
      "certainly":"확실히",
      "compliment":"칭찬, 경의",
      "decrease":"줄이다",
      "definite":"명확한",
      "dictate":"(조건, 방침 등을) 지시하다",
      "distinction":"차이",
      "embed":"고정시키다, 새겨 넣다",
      "escape":"피하다 / 도피",
      "essentially":"본래, 본질적으로",
      "forge":"~로 나아가다 / 만들다",
      "identity":"동일성",
      "illuminate":"명확히 하다; 밝게 하다",
      "in a short space of time":"단시간에, 빨리",
      "inconstant":"변하기 쉬운",
      "initial":"처음의",
      "lay off":"(일시적으로) 해고하다",
      "motif":"주제 / 문양",
      "patience":"인내",
      "perilous":"위험한",
      "personnel":"직원",
      "ready":"준비된",
      "refuse":"거절하다 / 쓰레기",
      "revival":"재생, 부활",
      "sorrow":"슬픔",
      "spend":"소비하다",
      "spot":"발견하다",
      "steadfast":"확고한",
      "tension":"긴장, 팽팽함",
      "ultimate":"궁극적인",
      "with respect to":"~에 대하여"
    }
  },
  "36": {
    "words": {
      "anger":"화나게 하다",
      "auxiliary":"보조적인",
      "bizarre":"기괴한",
      "broaden":"확장하다",
      "check":"조사하다 / 막다",
      "cite":"언급하다",
      "consensus":"합의",
      "cope with":"~에 잘 대처하다",
      "ebb":"쇠퇴하다, 약해지다 / 간조, 썰물",
      "elementary":"기초적인",
      "fashion":"유행 / 만들다 / 맞추다",
      "finance":"자금을 조달하다",
      "force":"힘",
      "legendary":"전설적인",
      "markedly":"현저하게",
      "obvious":"명백한",
      "output":"결과물",
      "overwhelmingly":"압도적으로",
      "pension":"연금",
      "pioneer":"개척하다",
      "potent":"강력한",
      "probe":"정밀 조사하다 / 조사",
      "quaint":"기이한",
      "react":"반응하다",
      "reap":"수확하다; 획득하다",
      "spectrum":"범위",
      "stock":"비축(물)",
      "strain":"잡아당기다 / 팽팽함, 긴장",
      "stroke":"일격",
      "sturdy":"튼튼한",
      "tactic(s)":"전술, 책략",
      "tapered":"좁아진",
      "upsurge":"급증",
      "utility":"실용성",
      "whereas":"~에 반하여",
      "widespread":"널리 퍼진, 광범위한"
    }
  },
  "37": {
    "words": {
      "accomplish":"성취하다",
      "accordingly":"따라서",
      "alarm":"공포, 놀람 / 놀라게 하다",
      "apparatus":"기구",
      "backbone":"중추; 척추",
      "bode":"징조가 되다",
      "cargo":"화물",
      "composition":"구성(물), 조직",
      "conduit":"도관, 선",
      "consider":"깊이 생각하다; 간주하다",
      "dual":"이중의",
      "encroach":"침입하다",
      "ensue":"뒤따라 일어나다",
      "equip":"(필요한 것을) 갖추어 주다",
      "establish":"설립하다",
      "exorbitant":"과도한",
      "explicit":"명백한",
      "frantic":"미친 (광란의)",
      "hectic":"매우 흥분한, 정신없이 분주한",
      "inaugurate":"개시하다",
      "incise":"새기다",
      "jubilant":"환희에 찬",
      "mode":"양식, 형태",
      "ominous":"불길한",
      "own":"인정하다",
      "perpetual":"끊임없는",
      "praiseworthy":"칭찬할 만한",
      "progressive":"진보적인",
      "provide":"제공하다",
      "provision":"식량",
      "puzzle over":"쩔쩔매다, 이리저리 생각하다",
      "ruinous":"파괴적인",
      "solicitation":"권유, 간청",
      "solicitude":"근심, 염려",
      "stray":"벗어나다, 이탈하다",
      "troublesome":"힘든 (성가신)",
      "unqualified":"절대적인",
      "weak":"약한",
      "witness":"목격하다 / 증거"
    }
  },
  "38": {
    "words": {
      "abhor":"혐오하다",
      "ambition":"야망",
      "bulk":"거대함(대량); 대부분",
      "charitable":"관대한, 자비로운",
      "conclusively":"결정적으로, 확실히",
      "confer":"수여하다",
      "deny":"부인하다",
      "echo":"반영하다; 반항하다 / 반복하다",
      "eerie":"기묘한",
      "emulate":"모방하다",
      "forestall":"미리 막다, 미리 손쓰다",
      "generally":"대부분, 주로",
      "glance":"흘긋 봄",
      "implement":"도구",
      "in terms of":"~에 관하여",
      "inveigh against":"통렬히 비판하다",
      "look":"보다",
      "monetary":"재정(금전)상의",
      "motion":"움직임, 동작",
      "obtain":"얻다",
      "outspoken":"솔직한",
      "pant":"숨을 헐떡이다 / 바지",
      "patchy":"고르지 않은",
      "precipitation":"촉진, 성급함",
      "promote":"촉진한다",
      "purified":"정화된",
      "recreational":"오락의, 휴양의",
      "recruit":"얻다, 모집하다",
      "seize":"움켜잡다",
      "structure":"구조 / 조직화하다",
      "surreal":"초현실적인",
      "synthesis":"통합체, 통합",
      "textile":"직물",
      "thereby":"그것에 의하여",
      "title":"권리",
      "transcend":"초월하다",
      "twig":"가지",
      "vulnerable":"(영향을) 받기 쉬운",
      "wholly":"완전히"
    }
  },
  "39": {
    "words": {
      "abrupt":"급한, 갑작스러운",
      "adequate":"충분한",
      "advocate":"주장하다, 지지하다 / 지지자",
      "appendix":"부록, 부가물",
      "appropriate":"적절한",
      "assumption":"가정",
      "bestow":"주다, 수여하다",
      "boldly":"용감하게",
      "choicest":"엄선된, 가장 좋은",
      "classic":"전형적인, 대표적인",
      "constitute":"구성하다",
      "deposit":"두다; 비축하다",
      "dogma":"신념, 신조",
      "employ":"이용하다",
      "endorse":"보증하다, 지지하다 / 배서(서명)하다",
      "exponential":"급격한",
      "foremost":"으뜸가는",
      "fragrance":"향기",
      "furthermore":"더욱이",
      "genetic":"유전(학)적인",
      "imposing":"강한 인상을 주는, 웅장한",
      "luxurious":"사치스러운",
      "matter":"물질 / 논점",
      "nurture":"양육하다",
      "offset":"상쇄하다",
      "partially":"부분적으로",
      "presumable":"있음직한",
      "principle":"원칙, 규범",
      "purveyor":"공급업자",
      "replace":"대체하다",
      "routine":"보통의, 일상적인",
      "scold":"꾸짖다",
      "sequence":"연속 / 순서",
      "startle":"깜짝 놀라게 하다",
      "typical":"일반적인, 전형적인",
      "unshakeable":"흔들리지 않는, 확고한",
      "yield":"내주다, 굴복하다 / 산출하다, 야기하다"
    }
  },
  "40": {
    "words": {
      "additive":"첨가제 / 부가적인",
      "antiseptic":"청결한, 위생적인",
      "assemble":"모으다 (collect)",
      "asymmetric":"균형을 잃은",
      "attire":"의상",
      "avid":"탐욕스러운 / 열심인, 열렬한",
      "basic":"기본",
      "bound":"경계",
      "cluster":"모이다 (group)",
      "complex":"복합 건물군 / 복잡한",
      "contrary":"반대의, 반대되는",
      "customary":"관례적인, 습관적인",
      "dangle":"매달리다",
      "devour":"게걸스레 먹다",
      "encapsulate":"요약하다, 집약하다",
      "faction":"파벌",
      "fragment":"조각, 부분",
      "ignite":"불을 붙이다",
      "impound":"가두다",
      "innocuous":"해가 없는",
      "link":"유대, 결합 / 관련짓다",
      "murmur":"투덜거리다, 중얼거리다",
      "persistent":"지속하는",
      "prospect":"가망성, 전망",
      "random":"마구잡이의",
      "realize":"알다, 이해하다",
      "reside in":"거주하다",
      "robust":"튼튼한, 강한",
      "satisfy":"만족시키다",
      "simple":"순진한",
      "stamina":"지구력, 체력",
      "staple":"중요 상품 / 기본적인, 주요한",
      "terminate":"끝내다",
      "treasure":"소중히 하다",
      "unequal":"불공평한, 균형을 잃은",
      "venture":"과감히 ~하다"
    }
  },
  "41": {
    "words": {
      "ache":"아프다",
      "advantageous":"이로운, 유익한",
      "altitude":"고도",
      "antiquity":"고대",
      "assist":"돕다",
      "brilliance":"광채",
      "celestial":"하늘의",
      "cleave":"(쪼개어) 나누다; 찢다 / 고수하다, 결합하다",
      "density":"농도, 밀도",
      "desperate":"필사적인; 절망적인",
      "encourage":"격려하다",
      "encumber":"(의무, 짐 등을) 지우다 / 저해하다",
      "enrich":"(질, 가차 등을) 높이다",
      "fade":"약해지다, 사라지다",
      "flee":"피하다, 도망하다",
      "follow suit":"따라핟",
      "gigantic":"거대한",
      "hygiene":"위생",
      "impressive":"인상적인, 감동적인",
      "instantaneous":"즉각적인",
      "lusty":"건장한, 원기왕성한",
      "mankind":"인류",
      "maturity":"성숙(기)",
      "mere":"단지, 대수롭지 않은",
      "modest":"겸손한; 예의바른 / 많지(크지) 않은",
      "persist":"지속되다",
      "pile":"모으다; 쌓다 / 더미",
      "pristine":"오염되지 않은",
      "proficient":"숙련된, 능숙한",
      "sacred":"신성한",
      "scruple":"망설임, 양심의 가책",
      "scrupulous":"세심한, 꼼꼼한 / 양심적인, 정직한",
      "strike":"치다, 공격하다 / 파업",
      "unravel":"해명하다, 풀다",
      "vulgar":"저속한"
    }
  },
  "42": {
    "words": {
      "account for":"~의 이유를 밝히다, 설명하다 / 차지하다",
      "adjourn":"연기하다 (delay)",
      "adopt":"~을 채택하다, 차용하다",
      "adore":"숭배하다, 존경하다",
      "artificial":"인위적인, 인조의",
      "attend":"돌보다, 시중들다",
      "band":"집단, 무리",
      "besides":"게다가",
      "circumstance":"상황",
      "crawl":"기어가다",
      "demolish":"파괴하다",
      "endure":"견디다",
      "enormous":"거대한",
      "fashionable":"유행하는",
      "formulate":"(명확히, 체계적으로) 말하다",
      "hang":"매달리다",
      "immobility":"부동 상태",
      "inflate":"팽창하다",
      "interrupt":"가로막다, 중단하다",
      "manipulation":"조작, 속임수",
      "marvelous":"경이로운, 놀랄만한",
      "nevertheless":"그럼에도 불구하고",
      "operate":"작동하다",
      "outlive":"살아남다, ~보다 더(오래) 살다",
      "practicable":"실행 가능한",
      "resist":"저항하다",
      "risky":"위험한",
      "saved":"구원된, 구제된",
      "severe":"극심한, 가차 없는 / 어려운, 까다로운",
      "spontaneous":"자발적인",
      "stagger":"비틀거리다, 동요하다 / 당황시키다",
      "thriller":"스릴을 주는 것",
      "toil":"힘들게 일하다",
      "touch off":"야기하다",
      "utterly":"완전히",
      "vacuum":"진공, 공허",
      "valid":"타당한",
      "withhold":"보류하다; 억제하다",
      "wonder":"경이로움, 놀라운 일"
    }
  },
  "43": {
    "words": {
      "advance":"진보하다",
      "applicability":"적절함, 적절성",
      "brittle":"부서지기 쉬운",
      "careful":"주의 깊은",
      "convert":"바꾸다",
      "core":"핵심",
      "countervail":"상쇄시키다",
      "curative":"치유하는",
      "disintegrate":"붕괴되다, 분해되다",
      "divest":"박탈하다",
      "drive":"억지로 ~하게 하다 / 운동",
      "entangle":"뒤얽히게 하다",
      "evolve":"서서히 발전하다",
      "extant":"현존하는",
      "hamper":"방해하다",
      "hide":"(짐승의) 가죽 / 숨기다, 감추다",
      "immoral":"부도덕한",
      "incipient":"초기의",
      "isolate":"격리시키다",
      "joint":"접합하다, 연결하다",
      "kindle":"불을 붙이다",
      "landscape":"풍경, 전망",
      "migrate":"이동하다, 이주하다",
      "milestone":"획기적인 사건",
      "novel":"새로운 / 신기한, 진기한",
      "out of the question":"불가능한",
      "phenomenal":"놀랄 만한",
      "plunge":"떨어뜨리다, 던져 넣다",
      "presently":"곧",
      "reckless":"무모한, 부주의한",
      "sensitive":"민감하게 반응하는",
      "serious":"심각한, 중대한",
      "simultaneous":"동시에 일어나는",
      "soar":"높이 솟다 / 급상승하다",
      "subservient":"부차적인, 종속적인",
      "subterranean":"지하의",
      "unlawful":"불법적인"
    }
  },
  "44": {
    "words": {
      "absorb":"흡수하다",
      "accuse":"고발하다, 비난하다",
      "a host of":"많은 수의",
      "apathetic":"무관심한",
      "array":"배열하다, 진열하다",
      "continual":"끊임없는",
      "design":"뜻을 품다, 계획하다",
      "discard":"버리다",
      "elapse":"경과하다",
      "furnish":"공급하다",
      "futile":"쓸모없는",
      "guard":"지키다",
      "locomotion":"운동, 이동",
      "metamorphose":"(~으로) 변형, 변화하다(시키다)",
      "misconception":"잘못된 생각, 오해",
      "multiplicity":"다양성; 다수",
      "native":"토착의; 선천적인",
      "needless to say":"말할 필요도 없이",
      "passive":"수동적인, 활기 없는",
      "predicate":"단언하다 / 기초를 두다",
      "presence":"존재",
      "progressively":"점차적으로",
      "pungent":"신랄한, (맛 등이) 자극적인",
      "recover":"되찾다, 회복시키다",
      "regardless of":"~에 개의치 않고",
      "remainder":"나머지",
      "reputation":"명성",
      "shelter":"보호하다, 숨겨 주다",
      "spur":"자극 / 자극하다",
      "suggest":"암시하다",
      "surge":"중가(상승)하다",
      "terminal":"최종의",
      "transverse":"가로지르는",
      "underscore":"강조하다",
      "upbraid":"꾸짖다",
      "vagabond":"방랑하는",
      "vague":"모호한",
      "veracious":"진실한",
      "vital":"필수적인",
      "withstand":"버티다"
    }
  },
  "45": {
    "words": {
      "abound":"풍부하다, 가득 차다",
      "abstract":"추상적인, 이론적인",
      "affliction":"고뇌, 고통",
      "attachment":"애착",
      "beckon":"호출하다",
      "complicate":"복잡하게 하다",
      "consecutive":"연속적인",
      "consist of":"~로 구성되다",
      "coordination":"공동작용",
      "crowd":"군중, 무리",
      "doctrine":"원칙, 교리, 주의",
      "drastically":"극심하게",
      "elegant":"우아한, 세련된",
      "entity":"개체, 실체",
      "era":"시대",
      "established":"확정된",
      "facet":"양상",
      "flourish":"번성하다",
      "hue":"빛깔, 색",
      "impair":"손상시키다, 약하게 하다",
      "inevitably":"불가피하게",
      "infinite":"무한한, 끊없는",
      "inflame":"노하게 하다, 자극하다",
      "influential":"영향력 있는, 유력한",
      "jeopardize":"위태롭게 하다",
      "marvel":"경이로움",
      "monotonous":"단조로운",
      "notable":"주목할만한",
      "novelty":"참신함, 진기함",
      "oath":"맹세",
      "on the contrary":"반대로",
      "photosynthesis":"광합성",
      "prodigious":"경이로운",
      "remedy":"치료(법)",
      "speculate about":"추측하다, 가정하다",
      "strictly":"엄격하게; 엄밀히 / 순전히",
      "trend":"경향",
      "unencumbered by":"~에 의해 방해받지 않는",
      "unwonted":"보통이 아닌, 드문",
      "vexing":"성가신, 짜증나는",
      "votary":"(측정 종교의) 신봉자"
    }
  },
  "46": {
    "words": {
      "alight":"내리다",
      "alternate":"번갈아 일어나다",
      "contain":"포함(수용)하다",
      "deter":"막다, 방해하다",
      "examine":"정밀 조사하다",
      "fast":"빠른",
      "gist":"핵심",
      "gleaming":"반짝이는, 빛나는",
      "guarantee":"보증하다",
      "hobby":"취미",
      "inadequate":"불충분한",
      "inborn":"선천적인",
      "inaccessible":"접근하기 어려운, 얻기 어려운",
      "inclination":"성향, 경향",
      "in proximity to":"~에 가까운",
      "insight":"통찰력, 직관",
      "intent":"의도",
      "intertwine":"뒤엉키다",
      "join":"연결하다, 결합하다 / 합류하다",
      "meddlesome":"간섭하는",
      "multiply":"증가하다",
      "myriad":"무수한",
      "naive":"꾸밈없는, 순진한",
      "outrage":"화나게 하다",
      "particularly":"특히",
      "principal":"주요한",
      "propel":"추진하다, 밀어내다",
      "rigorous":"혹독한, 엄격한 / 정밀한",
      "savor":"맛",
      "scramble":"뒤섞다",
      "seldom":"거의 ~않다",
      "simulated":"모조의, 가짜의",
      "slight":"사소한",
      "sporadic":"산발적인",
      "standstill":"정지",
      "systematic":"조직적인",
      "through":"~에 의하여",
      "versatile":"다방면의",
      "voluble":"입심 좋은, 유창한"
    }
  },
  "47": {
    "words": {
      "amiable":"상냥한",
      "arduous":"힘드는; 분투적인",
      "ascend":"올라가다",
      "atmosphere":"공기, 분위기",
      "awe":"경외심",
      "completely":"완전히",
      "cram":"(쑤셔) 넣다",
      "dilemma":"곤경",
      "discharge":"(군인, 환자 등을) 해방시키다 / 방출하다",
      "enlist":"입대하다",
      "enterprise":"(모험적인) 사업",
      "escalate":"차츰 확대되다, 오르다",
      "estimate":"평가하다",
      "green hand":"미숙한 사람",
      "inclined":"~의 경향이 있는 / 경사진, 기울어진",
      "incoherent":"두서 없는",
      "innovate":"혁신하다",
      "lading":"화물",
      "original":"독창적인 / 처음의",
      "outrageous":"지나친, 엄청난",
      "picture":"묘사하다",
      "preliminary":"서두의, 예비의",
      "preoccupation":"몰두, 강박관념",
      "preserve":"보호하다, 보존하다",
      "radiant":"빛나는",
      "research":"조사하다",
      "reverence":"존경",
      "reverse":"뒤집다",
      "right":"옳은, 적절한",
      "satire":"풍자",
      "segregate":"떼어놓다, 분리하다",
      "stable":"안정된",
      "strong":"강한",
      "tease":"괴롭히다",
      "tempting":"매력적인, 유혹하는",
      "type":"유형",
      "underlying":"근원적인, 기저의",
      "vein":"정맥"
    }
  },
  "48": {
    "words": {
      "absolutely":"전적으로",
      "caption":"표제",
      "categorize":"분류하다",
      "complicated":"복잡한",
      "conflicting":"상반(상충)되는",
      "gratify":"만족시키다",
      "in operation":"실시 중의, 효력을 가지는",
      "instrument":"수단, 방법 / 기구, 도구",
      "intrude":"침범(침해)하다",
      "key":"어조, (음악) 조 / 필수적인, 중요한",
      "legacy":"(전통적인) 유산",
      "manufacture":"(대규모로) 제조하다",
      "memorable":"기억할 만한, 인상적인",
      "narrow":"좁아지다; 한정하다",
      "occasion":"행사, 사건",
      "occasional":"가끔의",
      "oversee":"감독하다",
      "oversight":"실수",
      "peaceful":"평온한",
      "peak":"정점, 절정",
      "perforate":"구멍을 내다",
      "postulate":"요구하다",
      "quit":"그만두다; 시작하다",
      "reinforcement":"보강, 지원군",
      "remnant":"잔재, 자취",
      "remove":"끌어내다, 제거하다",
      "role":"역할, 기능",
      "shudder":"떨림, 전율",
      "spread out":"넓히다, 전개하다",
      "strip":"제거하다",
      "tactile":"촉각으로 알 수 있는",
      "temporary":"일시적인",
      "tendency":"경향, 성향",
      "underpinning":"기초, 기반",
      "unencumbered":"방해 없는",
      "version":"번역(물) / 이형, 판",
      "well-suited":"적절한",
      "whole":"전체의, 완전한",
      "wit":"재치"
    }
  },
  "49": {
    "words": {
      "absolve":"사면하다, 용서하다",
      "ambling":"느긋한",
      "barter":"교환하다, 교역하다",
      "bombard":"공격하다",
      "breeding":"번식",
      "bulky":"거대한",
      "depict":"묘사하다",
      "diminish":"줄다",
      "duration":"지속 기간",
      "emphasize":"강조하다",
      "exalted":"고귀한",
      "favor":"호의 / 찬성",
      "fervor":"열정",
      "foliage":"잎",
      "foster":"기르다",
      "free":"해방시키다",
      "further":"그 이상의, 여분의",
      "guide":"안내하다",
      "inaction":"활동하지 않음",
      "incursion":"침입",
      "indispensable":"필수적인",
      "inimical":"적대하는",
      "intervention":"간섭, 개입",
      "merge":"결합(융합)하다",
      "pattern":"도안, 무늬",
      "permanent":"불변의, 영구적인",
      "point":"요점",
      "praise":"칭송하다",
      "precarious":"불확실한; 다루기 어려운",
      "prototype":"원형, 모델",
      "rapidly":"급속히",
      "refine":"다듬어 좋게 하다",
      "rent":"임대하다, 임차하다",
      "source":"근원, 출처",
      "sparsely":"희박하게",
      "standpoint":"관점",
      "stint":"절약하다",
      "subsequently":"이후에",
      "terrestrial":"지상의, 속세의",
      "unbridled":"억제되지 않은"
    }
  },
  "50": {
    "words": {
      "acclaim":"갈채, 절찬 / 격찬하다, 환호하다",
      "active":"활기찬",
      "administer":"관리하다, 집행하다 / 가하다",
      "avail":"도움이 되다",
      "blossom":"번영하다",
      "cast":"던지다",
      "charge":"책임을 지우다",
      "chiefly":"주로",
      "coherent":"논리적인, 일관성 있는",
      "count":"중요하다",
      "discernible":"인식할 수 있는",
      "distinguished":"두드러진",
      "federate":"엽합하다",
      "frame":"만들다",
      "huge":"거대한",
      "inevitable":"불가피한",
      "inspire":"고무하다",
      "intention":"의향, 의도",
      "livelihood":"직업, 생계",
      "make":"만들다, 구성하다",
      "mark":"유명, 명성 / 표시하다",
      "mechanism":"도구 / 방법",
      "move":"감동시키다 / 나아가다, 이동하다",
      "oppress":"억압(학대)하다",
      "pronounced":"명백한, 뚜렷한",
      "reward":"보답, 보상",
      "ripe":"무르익은, 성숙한",
      "roam":"배회하다",
      "sheen":"광채",
      "situation":"상태, 처지",
      "slender":"날씬한; 연약한",
      "speed":"급속하게 진행하다, 서두르다",
      "sustenance":"음식, 양식",
      "understand":"이해하다",
      "unparalleled":"비길 데 없는",
      "unquestionable":"확실한",
      "veneration":"존경"
    }
  },
  "51": {
    "words": {
      "attempt":"시도하다",
      "beneath":"~할 가치가 없는",
      "cohere":"단합하다",
      "collect":"모으다, 쌓다",
      "count for nothing":"중요하지 않다",
      "creative":"창조적인",
      "disinterested":"공정한",
      "distinguishable":"구별되는",
      "erudite":"학식 있는",
      "exceptionally":"유난히",
      "final":"마지막의, 궁극적인",
      "for the sake of":"~를 위하여",
      "impartial":"공정한, 공평한",
      "impervious":"불침투성의",
      "impolite":"무례한",
      "indifference":"무관심",
      "induce":"설득하여 ~하게 하다",
      "inhabitant":"주민",
      "jolt":"충격",
      "luminous":"빛을 내는, 반짝이는",
      "negligible":"하찮은",
      "obscure":"애매한",
      "omnipresent":"어디에나 존재하는",
      "overpower":"압도하다",
      "peculiar":"색다른, 독특한",
      "prohibitively":"엄청나게",
      "prophetic":"예언적인",
      "proprietor":"소유주",
      "protrude":"튀어나오다",
      "proximity":"근접",
      "reliable":"믿을 수 있는",
      "resort to":"의지하다",
      "seek":"찾다, 추구하다 / 노력하다, 시도하다",
      "statue":"조각상",
      "straight away":"즉시",
      "string":"일련, 연속",
      "tangled":"뒤엉킨",
      "telling":"효과적인",
      "track":"~을 쫓아가다; 진로를 관찰하다",
      "traditional":"통상적인, 전통의",
      "underneath":"~의 아래에"
    }
  }
}